denoisers/__init__.py
denoisers/datamodule.py
denoisers/lightning_module.py
denoisers/losses.py
denoisers/metrics.py
denoisers/transforms.py
denoisers/utils.py
denoisers/datasets/__init__.py
denoisers/datasets/audio.py
denoisers/modeling/__init__.py
denoisers/modeling/modules.py
denoisers/modeling/unet1d/__init__.py
denoisers/modeling/unet1d/config.py
denoisers/modeling/unet1d/model.py
denoisers/modeling/unet1d/modules.py
denoisers/modeling/waveunet/__init__.py
denoisers/modeling/waveunet/config.py
denoisers/modeling/waveunet/model.py
denoisers/modeling/waveunet/modules.py
denoisers/scripts/__init__.py
denoisers/scripts/publish.py
denoisers/scripts/train.py
denoisers/testing/__init__.py
denoisers-0.2.0.dist-info/LICENSE
denoisers-0.2.0.dist-info/METADATA
denoisers-0.2.0.dist-info/WHEEL
denoisers-0.2.0.dist-info/entry_points.txt
denoisers-0.2.0.dist-info/top_level.txt
denoisers-0.2.0.dist-info/RECORD
