Metadata-Version: 2.1
Name: denoisers
Version: 0.2.0
Summary: A package for training audio denoisers
Author-email: Will Rice <wrice20@gmail.com>
Project-URL: Homepage, https://github.com/will-rice/denoisers
Project-URL: Bug Tracker, https://github.com/will-rice/denoisers/issues
Classifier: Programming Language :: Python :: 3
Classifier: License :: OSI Approved :: Apache Software License
Classifier: Operating System :: OS Independent
Requires-Python: >=3.9
License-File: LICENSE
Requires-Dist: mypy>=1.13.0
Requires-Dist: pydocstyle>=6.3.0
Requires-Dist: pytest>=8.3.3
Requires-Dist: pytorch-lightning>=2.4.0
Requires-Dist: ruff>=0.7.4
Requires-Dist: torch>=2.5.1
Requires-Dist: torchaudio>=2.5.1
Requires-Dist: torchvision>=0.20.1
Requires-Dist: wandb>=0.18.7
Requires-Dist: matplotlib>=3.9.2
Requires-Dist: pedalboard>=0.9.16
Requires-Dist: pydub>=0.25.1
Requires-Dist: pyroomacoustics>=0.8.2
Requires-Dist: pre-commit>=4.0.1
Requires-Dist: librosa>=0.10.2.post1
Requires-Dist: transformers>=4.46.3
Requires-Dist: audiomentations>=0.37.0
Requires-Dist: onnxruntime>=1.20.1
Requires-Dist: pesq>=0.0.4
